{
  "main": {
    "id": "e3ca7fd74647b9f6",
    "type": "split",
    "children": [
      {
        "id": "6eff3c0b43ee9101",
        "type": "tabs",
        "children": [
          {
            "id": "aa344a83fbb8a99a",
            "type": "leaf",
            "state": {
              "type": "markdown",
              "state": {
                "file": "Session Notes/Eclipse/Eclipse Campaign Journal.md",
                "mode": "source",
                "source": false
              },
              "icon": "lucide-file",
              "title": "Eclipse Campaign Journal"
            }
          },
          {
            "id": "344bc0a0e4f07cbd",
            "type": "leaf",
            "state": {
              "type": "markdown",
              "state": {
                "file": "Session Notes/Eclipse/Session 1 - Stirring in the Darkness.md",
                "mode": "source",
                "source": false
              },
              "icon": "lucide-file",
              "title": "Session 1 - Stirring in the Darkness"
            }
          },
          {
            "id": "453f5f0ff23ce149",
            "type": "leaf",
            "state": {
              "type": "markdown",
              "state": {
                "file": "World of Helodaria/Zitrumean Empire.md",
                "mode": "source",
                "source": false
              },
              "icon": "lucide-file",
              "title": "Zitrumean Empire"
            }
          },
          {
            "id": "210bd1e571299317",
            "type": "leaf",
            "state": {
              "type": "markdown",
              "state": {
                "file": "World of Helodaria/Zitrumea.md",
                "mode": "source",
                "source": false
              },
              "icon": "lucide-file",
              "title": "Zitrumea"
            }
          },
          {
            "id": "3643212ed11a8ad3",
            "type": "leaf",
            "state": {
              "type": "markdown",
              "state": {
                "file": "Disaton Revelre Capitulum.md",
                "mode": "source",
                "source": false
              },
              "icon": "lucide-file",
              "title": "Disaton Revelre Capitulum"
            }
          }
        ],
        "currentTab": 1
      }
    ],
    "direction": "vertical"
  },
  "left": {
    "id": "d7ebda78c129d618",
    "type": "split",
    "children": [
      {
        "id": "8ca0f1d486588d8e",
        "type": "tabs",
        "children": [
          {
            "id": "3b2a6831c271b3d7",
            "type": "leaf",
            "state": {
              "type": "file-explorer",
              "state": {
                "sortOrder": "alphabetical",
                "autoReveal": false
              },
              "icon": "lucide-folder-closed",
              "title": "Files"
            }
          },
          {
            "id": "ee81b9515bf62e4a",
            "type": "leaf",
            "state": {
              "type": "search",
              "state": {
                "query": "",
                "matchingCase": true,
                "explainSearch": false,
                "collapseAll": false,
                "extraContext": false,
                "sortOrder": "alphabetical"
              },
              "icon": "lucide-search",
              "title": "Search"
            }
          },
          {
            "id": "60144437ebeeb8fa",
            "type": "leaf",
            "state": {
              "type": "bookmarks",
              "state": {},
              "icon": "lucide-bookmark",
              "title": "Bookmarks"
            }
          }
        ]
      }
    ],
    "direction": "horizontal",
    "width": 315.5
  },
  "right": {
    "id": "ea35a9a317969db7",
    "type": "split",
    "children": [
      {
        "id": "5ece3774c37e9648",
        "type": "tabs",
        "dimension": 62.21153846153846,
        "children": [
          {
            "id": "4cb96e6d4287e8a5",
            "type": "leaf",
            "state": {
              "type": "markdown",
              "state": {
                "file": "General Notes and Ideas.md",
                "mode": "source",
                "source": false
              },
              "icon": "lucide-file",
              "title": "General Notes and Ideas"
            }
          },
          {
            "id": "b3c79ccde858898a",
            "type": "leaf",
            "state": {
              "type": "backlink",
              "state": {
                "file": "Session Notes/Eclipse/Eclipse Campaign Journal.md",
                "collapseAll": true,
                "extraContext": false,
                "sortOrder": "alphabetical",
                "showSearch": false,
                "searchQuery": "",
                "backlinkCollapsed": false,
                "unlinkedCollapsed": true
              },
              "icon": "links-coming-in",
              "title": "Backlinks for Eclipse Campaign Journal"
            }
          },
          {
            "id": "e26a69bedfa5e5f1",
            "type": "leaf",
            "state": {
              "type": "outgoing-link",
              "state": {
                "file": "Session Notes/Eclipse/Eclipse Campaign Journal.md",
                "linksCollapsed": false,
                "unlinkedCollapsed": true
              },
              "icon": "links-going-out",
              "title": "Outgoing links from Eclipse Campaign Journal"
            }
          },
          {
            "id": "dfa8baabc6155b2d",
            "type": "leaf",
            "state": {
              "type": "tag",
              "state": {
                "sortOrder": "frequency",
                "useHierarchy": true
              },
              "icon": "lucide-tags",
              "title": "Tags"
            }
          },
          {
            "id": "f913bfe3e075c876",
            "type": "leaf",
            "state": {
              "type": "outline",
              "state": {
                "file": "Session Notes/Eclipse/Eclipse Campaign Journal.md",
                "followCursor": false,
                "showSearch": false,
                "searchQuery": ""
              },
              "icon": "lucide-list",
              "title": "Outline of Eclipse Campaign Journal"
            }
          },
          {
            "id": "c21e89a76f4631bf",
            "type": "leaf",
            "state": {
              "type": "all-properties",
              "state": {
                "sortOrder": "frequency",
                "showSearch": false,
                "searchQuery": ""
              },
              "icon": "lucide-archive",
              "title": "All properties"
            }
          }
        ],
        "currentTab": 1
      },
      {
        "id": "92400877833113eb",
        "type": "tabs",
        "dimension": 37.78846153846154,
        "children": [
          {
            "id": "bf82f9f28d38c15b",
            "type": "leaf",
            "state": {
              "type": "markdown",
              "state": {
                "file": "Guidelines.md",
                "mode": "source",
                "source": false
              },
              "icon": "lucide-file",
              "title": "Guidelines"
            }
          },
          {
            "id": "c68b5dcf4c07320d",
            "type": "leaf",
            "state": {
              "type": "graph",
              "state": {},
              "icon": "lucide-git-fork",
              "title": "Graph view"
            }
          }
        ],
        "currentTab": 1
      }
    ],
    "direction": "horizontal",
    "width": 315.5,
    "collapsed": true
  },
  "left-ribbon": {
    "hiddenItems": {
      "obsidian-5e-statblocks:Open Creature pane": false,
      "switcher:Open quick switcher": false,
      "graph:Open graph view": false,
      "canvas:Create new canvas": false,
      "daily-notes:Open today's daily note": false,
      "templates:Insert template": false,
      "command-palette:Open command palette": false,
      "workspaces:Manage workspace layouts": false
    }
  },
  "active": "344bc0a0e4f07cbd",
  "lastOpenFiles": [
    "Session Notes/Eclipse/Eclipse Campaign Journal.md",
    "Disaton Revelre Capitulum.md",
    "Session Notes/Eclipse/Session 1 - Stirring in the Darkness.md",
    "Session Notes/Vanguard/Vanguard Campaign Journal.md",
    "Lord Harrenhal.md",
    "Session Notes/Vanguard/Session 84 - Travel to Steinwalde.md",
    "World of Helodaria/Zitrumea.md",
    "World of Helodaria/Helodarian Calendar.md",
    "World of Helodaria/Zitrumean Empire.md",
    "World of Helodaria/Syr Armond.md",
    "Session Notes/Vanguard/Vanguard Arc 6 - The Golden Age.md",
    "Session Notes/Eclipse/Session 0.md",
    "export/Session 0/Attachments/Pasted image 20250414132345.png",
    "export/Session 0/Attachments",
    "export/Session 0/plugin/chalkboard/README.md",
    "export/Session 0/plugin/chalkboard/_style.css",
    "export/Session 0/plugin/chalkboard/img/blackboard.png",
    "export/Session 0/plugin/chalkboard/img/boardmarker-black.png",
    "export/Session 0/plugin/chalkboard/img/boardmarker-blue.png",
    "export/Session 0/plugin/chalkboard/img/boardmarker-green.png",
    "export/Session 0/plugin/chalkboard/img/boardmarker-orange.png",
    "export/Session 0/plugin/chalkboard/img/boardmarker-purple.png",
    "export/Session 0/plugin/chalkboard/img/boardmarker-red.png",
    "export/Session 0/plugin/chalkboard/img/boardmarker-yellow.png",
    "export/Session 0/plugin/chalkboard/img/chalk-blue.png",
    "export/Session 0/plugin/chalkboard/img",
    "export/Session 0/plugin/chalkboard/plugin (copy).js",
    "export/Session 0/plugin/chalkboard/style.css",
    "export/Session 0/plugin/chalkboard/plugin.js",
    "export/Session 0/plugin/chalkboard",
    "export/Session 0/plugin/chart/plugin.js",
    "export/Session 0/plugin/chart/chart.min.js",
    "export/Session 0/plugin/chart/README.md",
    "export/Session 0/plugin/chart",
    "export/Session 0/plugin/customcontrols/README.md",
    "export/Session 0/plugin/menu/CONTRIBUTING.md",
    "export/Session 0/plugin/menu/README.md",
    "World of Helodaria/Prince Artorius Sirkon.md",
    "Session 0 Presentation.md",
    "World of Helodaria/Deities of Helodaria.md",
    "World of Helodaria/Trayfort Keep.md",
    "Session Notes/Vanguard/Session 83 - Through the Sirkonian Countryside.md",
    "World of Helodaria/Sirkonos.md",
    "World of Helodaria/Estravia.md",
    "World of Helodaria/Strahldale.md",
    "World of Helodaria/Steinefni Mining Company.md",
    "Ceaseless Arc Planning.canvas",
    "Ceaseless Arc.canvas"
  ]
}